pointwise/__init__.py
pointwise/glyph_client.py
pointwise/glyphapi/__init__.py
pointwise/glyphapi/glyphobj.py
pointwise/glyphapi/utilities.py
pointwise_glyph_client-2.0.13.dist-info/LICENSE
pointwise_glyph_client-2.0.13.dist-info/METADATA
pointwise_glyph_client-2.0.13.dist-info/WHEEL
pointwise_glyph_client-2.0.13.dist-info/top_level.txt
pointwise_glyph_client-2.0.13.dist-info/RECORD
