Metadata-Version: 2.1
Name: pointwise-glyph-client
Version: 2.0.13
Summary: Glyph client in Python with Python-like API to Pointwise Glyph Server
Home-page: http://github.com/pointwise/GlyphClientPython
Author: Cadence Design Systems, Inc.
Author-email: pw-pypi@cadence.com
License: UNKNOWN
Platform: UNKNOWN
Classifier: Programming Language :: Python :: 3.6
Classifier: Programming Language :: Python :: 3.7
Classifier: Programming Language :: Python :: 3.8
Classifier: Programming Language :: Python :: 3.9
Classifier: Programming Language :: Python :: 3.10
Classifier: Programming Language :: Python :: 3.11
Classifier: Programming Language :: Python :: 3.12
Classifier: Programming Language :: Python :: 2.7
License-File: LICENSE
Requires-Dist: numpy
